pypjt/__init__.py
pypjt/create.py
pypjt/pypjt.ts
pypjt/jslib/index.ts
pypjt/jslib/uniapp/network.ts
pypjt/templates/common/.dockerignore
pypjt/templates/common/.env.example
pypjt/templates/common/.gitattributes
pypjt/templates/common/.gitignore
pypjt/templates/common/.pre-commit-config.yaml
pypjt/templates/common/.readthedocs.yaml
pypjt/templates/common/.releaserc
pypjt/templates/common/Dockerfile
pypjt/templates/common/README.rst
pypjt/templates/common/commitlint.config.mjs
pypjt/templates/common/compose.yml
pypjt/templates/common/package-lock.json
pypjt/templates/common/package.json
pypjt/templates/common/.github/dependabot.yml
pypjt/templates/common/.github/actions/commit/action.yml
pypjt/templates/common/.github/actions/setup-test-env/action.yml
pypjt/templates/common/.github/scripts/update_version.py
pypjt/templates/common/.github/workflows/commitlint.yml
pypjt/templates/common/.github/workflows/lint.yml
pypjt/templates/common/.github/workflows/pre-commit.yml
pypjt/templates/common/.github/workflows/pypi.yml
pypjt/templates/common/.github/workflows/release.yml
pypjt/templates/common/.github/workflows/test.yml
pypjt/templates/common/.vscode/extensions.json
pypjt/templates/common/.vscode/settings.json
pypjt/templates/common/ansible/ansible.cfg
pypjt/templates/common/ansible/inventory.yml
pypjt/templates/common/ansible/site.yml
pypjt/templates/common/ansible/tasks/copy_env.yml
pypjt/templates/common/ansible/tasks/copy_files.yml
pypjt/templates/common/ansible/tasks/copy_other_files.yml
pypjt/templates/common/ansible/tasks/docker_prune_once.py
pypjt/templates/common/ansible/tasks/merge_env.py
pypjt/templates/common/ansible/tasks/run_docker.yml
pypjt/templates/common/docs/Makefile
pypjt/templates/common/docs/make.bat
pypjt/templates/common/docs/source/conf.py
pypjt/templates/common/docs/source/index.rst
pypjt/templates/common/scripts/build_and_upload_to_pypi
pypjt/templates/common/scripts/git_init
pypjt/templates/common/scripts/install_dep
pypjt-2.1.0.dist-info/licenses/LICENSE
pypjt-2.1.0.dist-info/METADATA
pypjt-2.1.0.dist-info/WHEEL
pypjt-2.1.0.dist-info/entry_points.txt
pypjt-2.1.0.dist-info/top_level.txt
pypjt-2.1.0.dist-info/RECORD
